pylauncher/__init__.py
pylauncher/hostlist3.py
pylauncher/pylauncher.py
pylauncher/pylauncher2.py
pylauncher-4.0.dist-info/LICENSE
pylauncher-4.0.dist-info/METADATA
pylauncher-4.0.dist-info/WHEEL
pylauncher-4.0.dist-info/top_level.txt
pylauncher-4.0.dist-info/RECORD
