Metadata-Version: 2.1
Name: pylauncher
Version: 4.0
Summary: Parametric job launcher
Home-page: https://github.com/TACC/pylauncher
Author: Victor Eijkhout
Author-email: eijkhout@tacc.utexas.edu
License: UNKNOWN
Project-URL: Bug Tracker, https://github.com/TACC/pylauncher/issues
Platform: UNKNOWN
Classifier: Programming Language :: Python :: 3
Classifier: License :: OSI Approved :: MIT License
Classifier: Operating System :: OS Independent
Requires-Python: >=3.8
License-File: LICENSE
